
{
    "formula_inputs":
    [
        {
            "model_state":"active",
            "name":"emissions_in_grams_per_km",
            "group_name":null,
            "base_unit":null,
            "values":
            {
                "co2":206,
                "co":0.504,
                "hc_and_nox":0.05,
                "hc":0.022,
                "nox":0,
                "particulates":0
            },
            "active_at":"2010-07-09T11:46:25Z",
            "input_units":"g/km",
            "label_input_units":"g/km",
            "main_source_id":"4c205dddd3aea93ba900000a",
            "id":"4c370c11ae2b7b418e002338"
        },
        {
            "model_state":"active",
            "name":"emissions_in_kg_per_km",
            "group_name":null,
            "base_unit":null,
            "values":
            {
                "co2":0.206,
                "co":0.000504,
                "hc_and_nox":5.0e-05,
                "hc":2.2e-05,
                "nox":0,
                "particulates":0
            },
            "active_at":"2010-07-09T11:46:25Z",
            "input_units":"kg/km",
            "label_input_units":"kg/km",
            "main_source_id":"4c205dddd3aea93ba900000a",
            "id":"4c370c11ae2b7b418e002339"
        },
        {
            "model_state":"active",
            "name":"emissions_in_kg_per_mile",
            "group_name":null,
            "base_unit":null,
            "values":
            {
                "co2":0.128002465552,
                "co":0.000313171080768,
                "hc_and_nox":3.10685596e-05,
                "hc":1.3670166224e-05,
                "nox":0,
                "particulates":0
            },
            "active_at":"2010-07-09T11:46:25Z",
            "input_units":"kg/mile",
            "label_input_units":"kg/mil",
            "main_source_id":"4c205dddd3aea93ba900000a",
            "id":"4c370c11ae2b7b418e00233a"
        },
        {
            "model_state":"active",
            "name":"fuel_consumption_in_litres_per_km",
            "group_name":null,
            "base_unit":null,
            "values":
            {
                "urban_cold":11.9,
                "extra_urban":6.7,
                "combined":8.6
            },
            "active_at":"2010-07-09T11:46:25Z",
            "input_units":"l/km",
            "label_input_units":"l/km",
            "main_source_id":"4c205dddd3aea93ba900000a",
            "id":"4c370c11ae2b7b418e00233b"
        },
        {
            "model_state":"active",
            "name":"fuel_consumption_in_miles_per_gallon",
            "group_name":null,
            "base_unit":null,
            "values":
            {
                "urban_cold":23.7378151260504,
                "extra_urban":42.1611940298507,
                "combined":32.846511627907
            },
            "active_at":"2010-07-09T11:46:25Z",
            "input_units":"mpg",
            "label_input_units":"mpg",
            "main_source_id":"4c205dddd3aea93ba900000a",
            "id":"4c370c11ae2b7b418e00233c"
        }
    ]
}